setup.py
dataspace_client/__init__.py
dataspace_client/dataspace.py
dataspace_client.egg-info/PKG-INFO
dataspace_client.egg-info/SOURCES.txt
dataspace_client.egg-info/dependency_links.txt
dataspace_client.egg-info/requires.txt
dataspace_client.egg-info/top_level.txt