Metadata-Version: 2.1
Name: dataspace-client
Version: 0.1.3.14
Summary: This is a tool for connecting to a dataspace created with publish subscribe paradigm.
Author: Anton Gustafsson
Author-email: anton.gustafsson@ri.se
Classifier: Programming Language :: Python :: 3
Classifier: License :: OSI Approved :: MIT License
Classifier: Operating System :: OS Independent
Requires-Python: >=3.6
Requires-Dist: paho-mqtt>=1.5.0
Requires-Dist: trimesh>=4.4.9
Requires-Dist: pandas>=2.2.2
Requires-Dist: pytz
